split_radix/fsm_control_unit.v
module control_unit_fsm_3rd_stage #(
    parameter stage_num_bits = 2,
    parameter Num_of_samples = 256,
    parameter step_size = 4,
    parameter Num_of_samples_bits = 8
)(
    input clock,
    input reset,
    input input_en,
    output reg step_mode_in,
    output reg step_mode_out,
    output reg [stage_num_bits+1:0] stride_segment_counter,
    output reg [stage_num_bits+1:0] butterfly_op_counter,
    output reg butterfly_op_counter_en
);

    // State encoding
    localparam IDLE = 3'b000;
    localparam FILL = 3'b001;
    localparam PROCESSING = 3'b010;
    localparam RESTART_OUT_COUNT = 3'b011;
    localparam RESTART_IN_COUNT = 3'b100;
    localparam FLUSH = 3'b101;

    reg [2:0] state;
    reg step_count_in, step_count_out;
    reg [Num_of_samples_bits-1:0] flush_count, input_count;

    // State transition logic
    always @(posedge clock or posedge reset) begin
        if (reset) begin
            state <= IDLE;
            stride_segment_counter  <= 0;
            butterfly_op_counter    <= 0;
            butterfly_op_counter_en <= 1'b0;
            flush_count             <= 0;
            step_mode_in            <= 1'b0;
            step_mode_out           <= 1'b0;
            step_count_in           <= 1'b1;
            step_count_out          <= 1'b1;
            input_count             <= 0;
        end else begin
            case (state)
                IDLE: begin
                    stride_segment_counter  <= 0;
                    butterfly_op_counter    <= 0;
                    butterfly_op_counter_en <= 1'b0;
                    step_mode_in            <= 1'b0;
                    step_mode_out           <= 1'b0;
                    step_count_in           <= 1'b1;
                    step_count_out          <= 1'b1;
                    flush_count             <= 0;
                    input_count             <= 0;

                    if (input_en) begin
                        state <= FILL;
                        stride_segment_counter  <= stride_segment_counter + 1'b1;
                        input_count <= input_count + 1'b1;
                    end else begin
                        state <= state;
                    end
                end
                FILL: begin
                    stride_segment_counter  <= stride_segment_counter + 1'b1;
                    input_count <= input_count + 1'b1;
                    butterfly_op_counter    <= 0;
                    butterfly_op_counter_en <= 1'b0;
                    step_mode_in            <= 1'b0;
                    step_mode_out           <= 1'b0;
                    step_count_in           <= 1'b1;
                    step_count_out          <= 1'b1;
                    flush_count             <= 0;

                    if(stride_segment_counter[stage_num_bits:0] == {1'b0, {(stage_num_bits+1-2){1'b1}}, 1'b0}) begin
                        state <= PROCESSING;
                        butterfly_op_counter_en <= 1'b1;
                        flush_count <= flush_count - 1'b1;
                    end else begin
                        state <= state;
                    end
                end
                PROCESSING: begin
                    if(!input_en) begin
                        state <= FLUSH;
                        stride_segment_counter  <= stride_segment_counter;
                        input_count <= input_count;
                        butterfly_op_counter <= butterfly_op_counter + 1'b1;
                        butterfly_op_counter_en <= 1'b1;
                        flush_count <= flush_count - 1'b1;
                        step_mode_out <= step_mode_out;
                        step_mode_in <= step_mode_in;
                        step_count_in <= step_count_in;
                        step_count_out <= step_count_out;
                    end else begin
                        input_count <= input_count + 1'b1;
                        butterfly_op_counter_en <= 1'b1;
                        flush_count <= flush_count - 1'b1;
                        step_mode_out <= step_mode_out;
                        step_mode_in <= step_mode_in;
                        step_count_in <= step_count_in;
                        step_count_out <= step_count_out;


                        if(stride_segment_counter[stage_num_bits:0] == {(stage_num_bits+1){1'b1}} && step_mode_in == 1'b0) begin
                            step_count_in <= 1'b1;
                            if(step_count_in == 1'b1) begin
                                step_mode_in <= 1'b1;
                                step_count_in <= 1'b0;
                            end
                        end else if(stride_segment_counter[stage_num_bits:0] == {(stage_num_bits+1){1'b1}} && step_mode_in == 1'b1) begin
                            step_mode_in <= 1'b0;
                        end 

                        if(butterfly_op_counter[stage_num_bits:0] == {(stage_num_bits+1){1'b1}} && step_mode_out == 1'b0) begin
                            step_count_out <= 1'b1;
                            if(step_count_out == 1'b1) begin
                                step_mode_out <= 1'b1;
                                step_count_out <= 1'b0;
                            end
                        end else if(butterfly_op_counter[stage_num_bits:0] == {(stage_num_bits+1){1'b1}} && step_mode_out == 1'b1) begin
                            step_mode_out <= 1'b0;
                        end 

                        if(stride_segment_counter[stage_num_bits:0] == {{(stage_num_bits+1){1'b1}}} && step_mode_in == 1'b1) begin
                            stride_segment_counter <= stride_segment_counter ^ {1'b0, {(stage_num_bits+1){1'b1}}};
                        end else begin
                            stride_segment_counter  <= stride_segment_counter + 1'b1;
                        end

                        if(butterfly_op_counter[stage_num_bits:0] == {{(stage_num_bits+1){1'b1}}} && step_mode_out == 1'b1) begin
                            butterfly_op_counter <= butterfly_op_counter ^ {1'b0, {(stage_num_bits+1){1'b1}}};
                        end else begin
                            butterfly_op_counter <= butterfly_op_counter + 1'b1;
                        end

                        if(input_count == { {(Num_of_samples_bits-1){1'b1}}, 1'b0 }) begin
                            state <= RESTART_IN_COUNT;
                        end else if(flush_count == 1) begin
                            state <= RESTART_OUT_COUNT;
                        end
                    end
                end
                RESTART_IN_COUNT: begin
                    //stride_segment_counter  <= stride_segment_counter ^ {1'b0, {(stage_num_bits+1){1'b1}}};
                    if(stride_segment_counter[stage_num_bits:0] == {{(stage_num_bits+1){1'b1}}} && step_mode_in == 1'b1) begin
                        stride_segment_counter <= stride_segment_counter ^ {1'b0, {(stage_num_bits+1){1'b1}}};
                    end else begin
                        stride_segment_counter  <= stride_segment_counter + 1'b1;
                    end

                    input_count <= input_count + 1'b1;
                    butterfly_op_counter <= butterfly_op_counter + 1'b1;
                    butterfly_op_counter_en <= 1'b1;
                    flush_count <= flush_count - 1'b1;
                    step_mode_out <= step_mode_out;
                    step_mode_in <= 1'b0;
                    step_count_in <= 1'b1;
                    step_count_out <= step_count_out;

                    if(!input_en) begin
                        state <= FLUSH;
                    end else begin
                        state <= PROCESSING;
                    end
                end
                RESTART_OUT_COUNT: begin
                    stride_segment_counter <= stride_segment_counter + 1'b1;
                    input_count <= input_count + 1'b1;
                    //butterfly_op_counter <= butterfly_op_counter ^ {1'b0, {(stage_num_bits+1){1'b1}}};
                    if(butterfly_op_counter[stage_num_bits:0] == {{(stage_num_bits+1){1'b1}}} && step_mode_out == 1'b1) begin
                        butterfly_op_counter <= butterfly_op_counter ^ {1'b0, {(stage_num_bits+1){1'b1}}};
                    end else begin
                        butterfly_op_counter <= butterfly_op_counter + 1'b1;
                    end

                    butterfly_op_counter_en <= 1'b1;
                    flush_count <= flush_count - 1'b1;
                    step_mode_out <= 1'b0;
                    step_mode_in <= step_mode_in;
                    step_count_in <= step_count_in;
                    step_count_out <= 1'b1;
                    
                    state <= PROCESSING;
                    
                end
                FLUSH: begin
                    stride_segment_counter  <= stride_segment_counter;
                    input_count <= input_count;
                    butterfly_op_counter <= butterfly_op_counter + 1'b1;
                    butterfly_op_counter_en <= 1'b1;
                    flush_count <= flush_count - 1'b1;
                    step_mode_out <= step_mode_out;
                    step_mode_in <= step_mode_in;
                    step_count_in <= step_count_in;
                    step_count_out <= step_count_out;

                    //If the input is disabled correclty the output step_mode 
                    //will not change until the flush_count is 0.

                    if(flush_count == 0) begin
                        state <= IDLE;
                    end else begin
                        state <= state;
                    end
                end
            endcase
        end
    end
endmodule

split_radix/tb_fsm_control_unit.v
`timescale 1ns / 1ps

module tb_control_unit_fsm_3rd_stage();

    // ----------------------------------------------------
    // 1. Parameters
    // ----------------------------------------------------
    // Kept identical to the module's default parameters
    parameter Num_of_samples = 256;
    parameter STAGE_NUM = 5;

    localparam stage_num_bits = $clog2(Num_of_samples/(4 * 2**(STAGE_NUM-2))) - 1;
    localparam step_size = Num_of_samples/(2**(STAGE_NUM-2));
    localparam Num_of_samples_bits = $clog2(Num_of_samples/4);
    // ----------------------------------------------------
    // 2. Signals
    // ----------------------------------------------------
    // Inputs (declared as reg to drive them in initial block)
    reg clock;
    reg reset;
    reg input_en;

    // Outputs (declared as wire to connect to module)
    wire step_mode_in;
    wire step_mode_out;
    wire [stage_num_bits+1:0] stride_segment_counter;
    wire [stage_num_bits+1:0] butterfly_op_counter;
    wire butterfly_op_counter_en;

    // ----------------------------------------------------
    // 3. Module Instantiation (UUT - Unit Under Test)
    // ----------------------------------------------------
    control_unit_fsm_3rd_stage #(
        .stage_num_bits(stage_num_bits),
        .Num_of_samples(Num_of_samples),
        .step_size(step_size),
        .Num_of_samples_bits(Num_of_samples_bits)
    ) uut (
        .clock(clock),
        .reset(reset),
        .input_en(input_en),
        .step_mode_in(step_mode_in),
        .step_mode_out(step_mode_out),
        .stride_segment_counter(stride_segment_counter),
        .butterfly_op_counter(butterfly_op_counter),
        .butterfly_op_counter_en(butterfly_op_counter_en)
    );

    // ----------------------------------------------------
    // 4. Clock Generation
    // ----------------------------------------------------
    // 10ns clock period (100 MHz)
    always #5 clock = ~clock;

    // ----------------------------------------------------
    // 5. Stimulus Generation
    // ----------------------------------------------------
    initial begin
        $dumpfile("tb_fsm_control_unit.vcd");
        $dumpvars(0, tb_control_unit_fsm_3rd_stage);

        // Initialize all inputs to known states
        clock = 0;
        reset = 1;
        input_en = 0;

        #20;
        reset = 0;
    
        #100;

        input_en = 1;

        #2560;

        input_en = 0;

        $display("Time %0t: Simulation Complete.", $time);

        #500
        $finish;
    end

endmodule

split_radix/fsm_sim.vcd
$date
	Wed Jul  1 01:36:13 2026
$end
$version
	Icarus Verilog
$end
$timescale
	1ps
$end
$scope module tb_control_unit_fsm_3rd_stage $end
$var wire 6 ! stride_segment_counter [5:0] $end
$var wire 1 " step_mode_out $end
$var wire 1 # step_mode_in $end
$var wire 1 $ butterfly_op_counter_en $end
$var wire 6 % butterfly_op_counter [5:0] $end
$var parameter 32 & Num_of_samples $end
$var parameter 32 ' Num_of_samples_bits $end
$var parameter 32 ( STAGE_NUM $end
$var parameter 33 ) stage_num_bits $end
$var parameter 32 * step_size $end
$var reg 1 + clock $end
$var reg 1 , input_en $end
$var reg 1 - reset $end
$scope module uut $end
$var wire 1 + clock $end
$var wire 1 , input_en $end
$var wire 1 - reset $end
$var parameter 3 . FILL $end
$var parameter 3 / FLUSH $end
$var parameter 3 0 IDLE $end
$var parameter 32 1 Num_of_samples $end
$var parameter 32 2 Num_of_samples_bits $end
$var parameter 3 3 PROCESSING $end
$var parameter 3 4 RESTART_IN_COUNT $end
$var parameter 3 5 RESTART_OUT_COUNT $end
$var parameter 33 6 stage_num_bits $end
$var parameter 32 7 step_size $end
$var reg 6 8 butterfly_op_counter [5:0] $end
$var reg 1 $ butterfly_op_counter_en $end
$var reg 6 9 flush_count [5:0] $end
$var reg 6 : input_count [5:0] $end
$var reg 3 ; state [2:0] $end
$var reg 1 < step_count_in $end
$var reg 1 = step_count_out $end
$var reg 1 # step_mode_in $end
$var reg 1 " step_mode_out $end
$var reg 6 > stride_segment_counter [5:0] $end
$upscope $end
$upscope $end
$enddefinitions $end
$comment Show the parameter values. $end
$dumpall
b10000000 7
b100 6
b11 5
b100 4
b10 3
b110 2
b100000000 1
b0 0
b110 /
b1 .
b10000000 *
b100 )
b11 (
b110 '
b100000000 &
$end
#0
$dumpvars
b100000 >
1=
1<
b0 ;
b0 :
b0 9
b100000 8
1-
0,
0+
b100000 %
0$
0#
0"
b100000 !
$end
#5000
1+
#10000
0+
#15000
1+
#20000
0+
0-
#25000
1+
#30000
0+
#35000
1+
#40000
0+
#45000
1+
#50000
0+
#55000
1+
#60000
0+
#65000
1+
#70000
0+
#75000
1+
#80000
0+
#85000
1+
#90000
0+
#95000
1+
#100000
0+
#105000
1+
#110000
0+
#115000
1+
#120000
0+
1,
#125000
b1 :
b100001 !
b100001 >
b1 ;
1+
#130000
0+
#135000
b10 :
b100010 !
b100010 >
1+
#140000
0+
#145000
b11 :
b100011 !
b100011 >
1+
#150000
0+
#155000
b100 :
b100100 !
b100100 >
1+
#160000
0+
#165000
b101 :
b100101 !
b100101 >
1+
#170000
0+
#175000
b110 :
b100110 !
b100110 >
1+
#180000
0+
#185000
b111 :
b100111 !
b100111 >
1+
#190000
0+
#195000
b1000 :
b101000 !
b101000 >
1+
#200000
0+
#205000
b1001 :
b101001 !
b101001 >
1+
#210000
0+
#215000
b1010 :
b101010 !
b101010 >
1+
#220000
0+
#225000
b1011 :
b101011 !
b101011 >
1+
#230000
0+
#235000
b1100 :
b101100 !
b101100 >
1+
#240000
0+
#245000
b1101 :
b101101 !
b101101 >
1+
#250000
0+
#255000
b1110 :
b101110 !
b101110 >
1+
#260000
0+
#265000
b111111 9
1$
b10 ;
b1111 :
b101111 !
b101111 >
1+
#270000
0+
#275000
b100001 %
b100001 8
b110000 !
b110000 >
b111110 9
b10000 :
1+
#280000
0+
#285000
b100010 %
b100010 8
b110001 !
b110001 >
b111101 9
b10001 :
1+
#290000
0+
#295000
b100011 %
b100011 8
b110010 !
b110010 >
b111100 9
b10010 :
1+
#300000
0+
#305000
b100100 %
b100100 8
b110011 !
b110011 >
b111011 9
b10011 :
1+
#310000
0+
#315000
b100101 %
b100101 8
b110100 !
b110100 >
b111010 9
b10100 :
1+
#320000
0+
#325000
b100110 %
b100110 8
b110101 !
b110101 >
b111001 9
b10101 :
1+
#330000
0+
#335000
b100111 %
b100111 8
b110110 !
b110110 >
b111000 9
b10110 :
1+
#340000
0+
#345000
b101000 %
b101000 8
b110111 !
b110111 >
b110111 9
b10111 :
1+
#350000
0+
#355000
b101001 %
b101001 8
b111000 !
b111000 >
b110110 9
b11000 :
1+
#360000
0+
#365000
b101010 %
b101010 8
b111001 !
b111001 >
b110101 9
b11001 :
1+
#370000
0+
#375000
b101011 %
b101011 8
b111010 !
b111010 >
b110100 9
b11010 :
1+
#380000
0+
#385000
b101100 %
b101100 8
b111011 !
b111011 >
b110011 9
b11011 :
1+
#390000
0+
#395000
b101101 %
b101101 8
b111100 !
b111100 >
b110010 9
b11100 :
1+
#400000
0+
#405000
b101110 %
b101110 8
b111101 !
b111101 >
b110001 9
b11101 :
1+
#410000
0+
#415000
b101111 %
b101111 8
b111110 !
b111110 >
b110000 9
b11110 :
1+
#420000
0+
#425000
b110000 %
b110000 8
b111111 !
b111111 >
b101111 9
b11111 :
1+
#430000
0+
#435000
b110001 %
b110001 8
b0 !
b0 >
0<
1#
b101110 9
b100000 :
1+
#440000
0+
#445000
b110010 %
b110010 8
b1 !
b1 >
b101101 9
b100001 :
1+
#450000
0+
#455000
b110011 %
b110011 8
b10 !
b10 >
b101100 9
b100010 :
1+
#460000
0+
#465000
b110100 %
b110100 8
b11 !
b11 >
b101011 9
b100011 :
1+
#470000
0+
#475000
b110101 %
b110101 8
b100 !
b100 >
b101010 9
b100100 :
1+
#480000
0+
#485000
b110110 %
b110110 8
b101 !
b101 >
b101001 9
b100101 :
1+
#490000
0+
#495000
b110111 %
b110111 8
b110 !
b110 >
b101000 9
b100110 :
1+
#500000
0+
#505000
b111000 %
b111000 8
b111 !
b111 >
b100111 9
b100111 :
1+
#510000
0+
#515000
b111001 %
b111001 8
b1000 !
b1000 >
b100110 9
b101000 :
1+
#520000
0+
0,
#525000
b110 ;
1+
#530000
0+
#535000
b100101 9
b111010 %
b111010 8
1+
#540000
0+
1,
#545000
b100100 9
b111011 %
b111011 8
1+
#550000
0+
#555000
b100011 9
b111100 %
b111100 8
1+
#560000
0+
#565000
b100010 9
b111101 %
b111101 8
1+
#570000
0+
#575000
b100001 9
b111110 %
b111110 8
1+
#580000
0+
#585000
b100000 9
b111111 %
b111111 8
1+
#590000
0+
#595000
b11111 9
b0 %
b0 8
1+
#600000
0+
#605000
b11110 9
b1 %
b1 8
1+
#610000
0+
#615000
b11101 9
b10 %
b10 8
1+
#620000
0+
#625000
b11100 9
b11 %
b11 8
1+
#630000
0+
#635000
b11011 9
b100 %
b100 8
1+
#640000
0+
#645000
b11010 9
b101 %
b101 8
1+
#650000
0+
#655000
b11001 9
b110 %
b110 8
1+
#660000
0+
#665000
b11000 9
b111 %
b111 8
1+
#670000
0+
#675000
b10111 9
b1000 %
b1000 8
1+
#680000
0+
#685000
b10110 9
b1001 %
b1001 8
1+
#690000
0+
#695000
b10101 9
b1010 %
b1010 8
1+
#700000
0+
#705000
b10100 9
b1011 %
b1011 8
1+
#710000
0+
#715000
b10011 9
b1100 %
b1100 8
1+
#720000
0+
#725000
b10010 9
b1101 %
b1101 8
1+
#730000
0+
#735000
b10001 9
b1110 %
b1110 8
1+
#740000
0+
#745000
b10000 9
b1111 %
b1111 8
1+
#750000
0+
#755000
b1111 9
b10000 %
b10000 8
1+
#760000
0+
#765000
b1110 9
b10001 %
b10001 8
1+
#770000
0+
#775000
b1101 9
b10010 %
b10010 8
1+
#780000
0+
#785000
b1100 9
b10011 %
b10011 8
1+
#790000
0+
#795000
b1011 9
b10100 %
b10100 8
1+
#800000
0+
#805000
b1010 9
b10101 %
b10101 8
1+
#810000
0+
#815000
b1001 9
b10110 %
b10110 8
1+
#820000
0+
#825000
b1000 9
b10111 %
b10111 8
1+
#830000
0+
#835000
b111 9
b11000 %
b11000 8
1+
#840000
0+
#845000
b110 9
b11001 %
b11001 8
1+
#850000
0+
#855000
b101 9
b11010 %
b11010 8
1+
#860000
0+
#865000
b100 9
b11011 %
b11011 8
1+
#870000
0+
#875000
b11 9
b11100 %
b11100 8
1+
#880000
0+
#885000
b10 9
b11101 %
b11101 8
1+
#890000
0+
#895000
b1 9
b11110 %
b11110 8
1+
#900000
0+
#905000
b0 9
b11111 %
b11111 8
1+
#910000
0+
#915000
b0 ;
b111111 9
b100000 %
b100000 8
1+
#920000
0+
#925000
b1 ;
b101001 :
b0 9
1<
0#
0$
b1001 !
b1001 >
1+
#930000
0+
#935000
b101010 :
b1010 !
b1010 >
1+
#940000
0+
#945000
b101011 :
b1011 !
b1011 >
1+
#950000
0+
#955000
b101100 :
b1100 !
b1100 >
1+
#960000
0+
#965000
b101101 :
b1101 !
b1101 >
1+
#970000
0+
#975000
b101110 :
b1110 !
b1110 >
1+
#980000
0+
#985000
b111111 9
1$
b10 ;
b101111 :
b1111 !
b1111 >
1+
#990000
0+
#995000
b100001 %
b100001 8
b10000 !
b10000 >
b111110 9
b110000 :
1+
#1000000
0+
#1005000
b100010 %
b100010 8
b10001 !
b10001 >
b111101 9
b110001 :
1+
#1010000
0+
#1015000
b100011 %
b100011 8
b10010 !
b10010 >
b111100 9
b110010 :
1+
#1020000
0+
#1025000
b100100 %
b100100 8
b10011 !
b10011 >
b111011 9
b110011 :
1+
#1030000
0+
#1035000
b100101 %
b100101 8
b10100 !
b10100 >
b111010 9
b110100 :
1+
#1040000
0+
#1045000
b100110 %
b100110 8
b10101 !
b10101 >
b111001 9
b110101 :
1+
#1050000
0+
#1055000
b100111 %
b100111 8
b10110 !
b10110 >
b111000 9
b110110 :
1+
#1060000
0+
#1065000
b101000 %
b101000 8
b10111 !
b10111 >
b110111 9
b110111 :
1+
#1070000
0+
#1075000
b101001 %
b101001 8
b11000 !
b11000 >
b110110 9
b111000 :
1+
#1080000
0+
#1085000
b101010 %
b101010 8
b11001 !
b11001 >
b110101 9
b111001 :
1+
#1090000
0+
#1095000
b101011 %
b101011 8
b11010 !
b11010 >
b110100 9
b111010 :
1+
#1100000
0+
#1105000
b101100 %
b101100 8
b11011 !
b11011 >
b110011 9
b111011 :
1+
#1110000
0+
#1115000
b101101 %
b101101 8
b11100 !
b11100 >
b110010 9
b111100 :
1+
#1120000
0+
#1125000
b101110 %
b101110 8
b11101 !
b11101 >
b110001 9
b111101 :
1+
#1130000
0+
#1135000
b101111 %
b101111 8
b11110 !
b11110 >
b110000 9
b111110 :
1+
#1140000
0+
#1145000
b100 ;
b110000 %
b110000 8
b11111 !
b11111 >
b101111 9
b111111 :
1+
#1150000
0+
#1155000
b10 ;
b101110 9
b110001 %
b110001 8
b0 :
b100000 !
b100000 >
1+
#1160000
0+
#1165000
b110010 %
b110010 8
b100001 !
b100001 >
b101101 9
b1 :
1+
#1170000
0+
#1175000
b110011 %
b110011 8
b100010 !
b100010 >
b101100 9
b10 :
1+
#1180000
0+
#1185000
b110100 %
b110100 8
b100011 !
b100011 >
b101011 9
b11 :
1+
#1190000
0+
#1195000
b110101 %
b110101 8
b100100 !
b100100 >
b101010 9
b100 :
1+
#1200000
0+
#1205000
b110110 %
b110110 8
b100101 !
b100101 >
b101001 9
b101 :
1+
#1210000
0+
#1215000
b110111 %
b110111 8
b100110 !
b100110 >
b101000 9
b110 :
1+
#1220000
0+
#1225000
b111000 %
b111000 8
b100111 !
b100111 >
b100111 9
b111 :
1+
#1230000
0+
#1235000
b111001 %
b111001 8
b101000 !
b101000 >
b100110 9
b1000 :
1+
#1240000
0+
#1245000
b111010 %
b111010 8
b101001 !
b101001 >
b100101 9
b1001 :
1+
#1250000
0+
#1255000
b111011 %
b111011 8
b101010 !
b101010 >
b100100 9
b1010 :
1+
#1260000
0+
#1265000
b111100 %
b111100 8
b101011 !
b101011 >
b100011 9
b1011 :
1+
#1270000
0+
#1275000
b111101 %
b111101 8
b101100 !
b101100 >
b100010 9
b1100 :
1+
#1280000
0+
#1285000
b111110 %
b111110 8
b101101 !
b101101 >
b100001 9
b1101 :
1+
#1290000
0+
#1295000
b111111 %
b111111 8
b101110 !
b101110 >
b100000 9
b1110 :
1+
#1300000
0+
#1305000
b0 %
b0 8
b101111 !
b101111 >
0=
1"
b11111 9
b1111 :
1+
#1310000
0+
#1315000
b1 %
b1 8
b110000 !
b110000 >
b11110 9
b10000 :
1+
#1320000
0+
#1325000
b10 %
b10 8
b110001 !
b110001 >
b11101 9
b10001 :
1+
#1330000
0+
#1335000
b11 %
b11 8
b110010 !
b110010 >
b11100 9
b10010 :
1+
#1340000
0+
#1345000
b100 %
b100 8
b110011 !
b110011 >
b11011 9
b10011 :
1+
#1350000
0+
#1355000
b101 %
b101 8
b110100 !
b110100 >
b11010 9
b10100 :
1+
#1360000
0+
#1365000
b110 %
b110 8
b110101 !
b110101 >
b11001 9
b10101 :
1+
#1370000
0+
#1375000
b111 %
b111 8
b110110 !
b110110 >
b11000 9
b10110 :
1+
#1380000
0+
#1385000
b1000 %
b1000 8
b110111 !
b110111 >
b10111 9
b10111 :
1+
#1390000
0+
#1395000
b1001 %
b1001 8
b111000 !
b111000 >
b10110 9
b11000 :
1+
#1400000
0+
#1405000
b1010 %
b1010 8
b111001 !
b111001 >
b10101 9
b11001 :
1+
#1410000
0+
#1415000
b1011 %
b1011 8
b111010 !
b111010 >
b10100 9
b11010 :
1+
#1420000
0+
#1425000
b1100 %
b1100 8
b111011 !
b111011 >
b10011 9
b11011 :
1+
#1430000
0+
#1435000
b1101 %
b1101 8
b111100 !
b111100 >
b10010 9
b11100 :
1+
#1440000
0+
#1445000
b1110 %
b1110 8
b111101 !
b111101 >
b10001 9
b11101 :
1+
#1450000
0+
#1455000
b1111 %
b1111 8
b111110 !
b111110 >
b10000 9
b11110 :
1+
#1460000
0+
#1465000
b10000 %
b10000 8
b111111 !
b111111 >
b1111 9
b11111 :
1+
#1470000
0+
#1475000
b10001 %
b10001 8
b0 !
b0 >
0<
1#
b1110 9
b100000 :
1+
#1480000
0+
#1485000
b10010 %
b10010 8
b1 !
b1 >
b1101 9
b100001 :
1+
#1490000
0+
#1495000
b10011 %
b10011 8
b10 !
b10 >
b1100 9
b100010 :
1+
#1500000
0+
#1505000
b10100 %
b10100 8
b11 !
b11 >
b1011 9
b100011 :
1+
#1510000
0+
#1515000
b10101 %
b10101 8
b100 !
b100 >
b1010 9
b100100 :
1+
#1520000
0+
#1525000
b10110 %
b10110 8
b101 !
b101 >
b1001 9
b100101 :
1+
#1530000
0+
#1535000
b10111 %
b10111 8
b110 !
b110 >
b1000 9
b100110 :
1+
