split_radix/memory_first_stage.v
`timescale 1ns / 1ps

module memory_first_stage #(
    parameter WIDTH = 32,
    parameter DEPTH = 16, 
    parameter stage_num_bits = 1
)(
    input clock,
    input reset,
    input [stage_num_bits:0] stride_segment_counter,
    input [stage_num_bits:0] butterfly_op_counter,
    input [stage_num_bits+1:0] mem_counter,
    input [stage_num_bits+1:0] mem_counter_read,
    input [WIDTH-1:0] input_real_0, input_real_1, input_real_2, input_real_3,
    input [WIDTH-1:0] input_imag_0, input_imag_1, input_imag_2, input_imag_3,
    output [WIDTH-1:0] output_imag_0, output_imag_1, output_imag_2, output_imag_3,
    output [WIDTH-1:0] output_real_0, output_real_1, output_real_2, output_real_3
);

    localparam inter_offset_size = $clog2(DEPTH);
    localparam intra_offset_size = inter_offset_size - 2;
    localparam vertical_offset_1 = 1 << intra_offset_size;
    localparam vertical_offset_2 = 2 << intra_offset_size;
    localparam vertical_offset_3 = 3 << intra_offset_size;

    //Normally for big ennough memories the synthesis tool will use block rams
     (* ram_style = "block" *) reg [2*WIDTH-1:0] mem_A [0:2*DEPTH-1];
     (* ram_style = "block" *) reg [2*WIDTH-1:0] mem_B [0:2*DEPTH-1];
     (* ram_style = "block" *) reg [2*WIDTH-1:0] mem_C [0:2*DEPTH-1];
     (* ram_style = "block" *) reg [2*WIDTH-1:0] mem_D [0:2*DEPTH-1];

    //Split memory into 4 different banks in order for each one to have 2 ports 
    //1 read and one write this help the tools use brams when the arrays are large enough
//    reg [2*WIDTH-1:0] mem_A [0:2*DEPTH-1];
//    reg [2*WIDTH-1:0] mem_B [0:2*DEPTH-1];
//    reg [2*WIDTH-1:0] mem_C [0:2*DEPTH-1];
//    reg [2*WIDTH-1:0] mem_D [0:2*DEPTH-1];

    wire [inter_offset_size:0] offset;
    
    // Final Output Registers
    reg [2*WIDTH-1:0] output_0, output_1, output_2, output_3;

    reg [inter_offset_size+1:0] ea_addr_A, ea_addr_B, ea_addr_C, ea_addr_D;

    wire [inter_offset_size+1:0] position_count;
    
    //This is usefull to calculate the read address for stages > 2
    //For the 1st stage there is no memory 
    //For the 2nd stage position count is not needed to calculate the read address
    generate
        if (DEPTH > 4) begin
            assign position_count = butterfly_op_counter[stage_num_bits:2];
        end else begin
            assign position_count = 0;
        end
    endgenerate

    //Read adreess calculation 
    wire [inter_offset_size+1:0] next_addr0;
    wire [inter_offset_size+1:0] next_addr1;
    wire [inter_offset_size+1:0] next_addr2;
    wire [inter_offset_size+1:0] next_addr3;

    if(DEPTH < 4) begin : special_addresses_for_8_point_fft
        assign next_addr0 = offset;
        assign next_addr1 = offset + 1'b1;
        assign next_addr2 = offset;
        assign next_addr3 = offset + 1'b1;
    end else begin
        assign next_addr0 = offset + position_count;
        assign next_addr1 = offset + vertical_offset_1 + position_count;
        assign next_addr2 = offset + vertical_offset_2 + position_count;
        assign next_addr3 = offset + vertical_offset_3 + position_count;
    end

    //Note for later
    //In order to facilitate the different input pattern in this first_radix_slit_stage we have the interchange 
    //position_count with butterfly_op_counter[stage_num_bits:stage_num_bits-1] so the access is correct.

    //Registers to hold data out of memory before output muxing
    reg [2*WIDTH-1:0] pipe_rdata_A, pipe_rdata_B, pipe_rdata_C, pipe_rdata_D;

    //Registers to delay the select signal for output muxing
    reg [stage_num_bits:0] pipe1_op, pipe2_op; 

    //Calculate the offset that is needed in order to go to the second part of the memory 
    //While in the first part new data is written
    //This is needed beacause the read and write patters are different and is we had only one part
    //While new data would have be written old data that hadnt be read yet would be overwritten
    //Theoretically is the pattern was the same we wouldnt need two parts
    assign offset = (mem_counter_read[stage_num_bits+1] == 0) ? {(inter_offset_size+1){1'b0}} : {1'b1, {(inter_offset_size){1'b0}}};



    if(DEPTH >= 4) begin : memory_logic
        always@(posedge clock) begin 
            if(reset) begin
                output_0 <= 0; 
                output_1 <= 0; 
                output_2 <= 0; 
                output_3 <= 0;
                pipe_rdata_A <= 0; 
                pipe_rdata_B <= 0; 
                pipe_rdata_C <= 0; 
                pipe_rdata_D <= 0;
                ea_addr_A <= 0; 
                ea_addr_B <= 0; 
                ea_addr_C <= 0; 
                ea_addr_D <= 0;
                pipe1_op <= 0; 
                pipe2_op <= 0;
            end else begin
                //Write input data in memory depending on the stide sigment we are currently in.
                if(stride_segment_counter[stage_num_bits:stage_num_bits-1] == 2'b00) begin
                    mem_A[mem_counter] <= {input_real_0, input_imag_0};
                    mem_B[mem_counter] <= {input_real_1, input_imag_1};
                    mem_C[mem_counter] <= {input_real_2, input_imag_2};
                    mem_D[mem_counter] <= {input_real_3, input_imag_3};
                end 
                else if(stride_segment_counter[stage_num_bits:stage_num_bits-1] == 2'b01) begin
                    mem_A[mem_counter] <= {input_real_3, input_imag_3};
                    mem_B[mem_counter] <= {input_real_0, input_imag_0};
                    mem_C[mem_counter] <= {input_real_1, input_imag_1};
                    mem_D[mem_counter] <= {input_real_2, input_imag_2};
                end 
                else if(stride_segment_counter[stage_num_bits:stage_num_bits-1] == 2'b10) begin
                    mem_A[mem_counter] <= {input_real_2, input_imag_2};
                    mem_B[mem_counter] <= {input_real_3, input_imag_3};
                    mem_C[mem_counter] <= {input_real_0, input_imag_0};
                    mem_D[mem_counter] <= {input_real_1, input_imag_1};
                end
                else if(stride_segment_counter[stage_num_bits:stage_num_bits-1] == 2'b11) begin
                    mem_A[mem_counter] <= {input_real_1, input_imag_1};
                    mem_B[mem_counter] <= {input_real_2, input_imag_2};
                    mem_C[mem_counter] <= {input_real_3, input_imag_3};
                    mem_D[mem_counter] <= {input_real_0, input_imag_0};
                end

                //Read stage 1 calculate the effective address before memory read
                //To easy the jod of the synthsys tools and maximize frequency

                pipe1_op <= butterfly_op_counter; //Register the read muxing signal 

                // Determine which address each memory needs to read
                case (butterfly_op_counter[1:0])
                    2'b00: ea_addr_A <= next_addr0; 
                    2'b01: ea_addr_A <= next_addr3;
                    2'b10: ea_addr_A <= next_addr2;
                    2'b11: ea_addr_A <= next_addr1;
                endcase

                case (butterfly_op_counter[1:0])
                    2'b00: ea_addr_B <= next_addr1;
                    2'b01: ea_addr_B <= next_addr0;
                    2'b10: ea_addr_B <= next_addr3;
                    2'b11: ea_addr_B <= next_addr2;
                endcase

                case (butterfly_op_counter[1:0])
                    2'b00: ea_addr_C <= next_addr2;
                    2'b01: ea_addr_C <= next_addr1;
                    2'b10: ea_addr_C <= next_addr0;
                    2'b11: ea_addr_C <= next_addr3;
                endcase

                case (butterfly_op_counter[1:0])
                    2'b00: ea_addr_D <= next_addr3;
                    2'b01: ea_addr_D <= next_addr2;
                    2'b10: ea_addr_D <= next_addr1;
                    2'b11: ea_addr_D <= next_addr0;
                endcase

                //Read stage 2 read from memory and store in pipe registers 
                pipe2_op <= pipe1_op;  //Register the read muxing signal 
                
                pipe_rdata_A <= mem_A[ea_addr_A];
                pipe_rdata_B <= mem_B[ea_addr_B];
                pipe_rdata_C <= mem_C[ea_addr_C];
                pipe_rdata_D <= mem_D[ea_addr_D];

                //Read stage 3 output muxing
                if(pipe2_op[1:0] == 2'b00) begin
                    output_0 <= pipe_rdata_A;
                    output_1 <= pipe_rdata_B;
                    output_2 <= pipe_rdata_C;
                    output_3 <= pipe_rdata_D;
                end
                else if(pipe2_op[1:0] == 2'b01) begin
                    output_0 <= pipe_rdata_B;
                    output_1 <= pipe_rdata_C;
                    output_2 <= pipe_rdata_D;
                    output_3 <= pipe_rdata_A;
                end
                else if(pipe2_op[1:0] == 2'b10) begin
                    output_0 <= pipe_rdata_C;
                    output_1 <= pipe_rdata_D;
                    output_2 <= pipe_rdata_A;
                    output_3 <= pipe_rdata_B;
                end
                else if(pipe2_op[1:0] == 2'b11) begin
                    output_0 <= pipe_rdata_D;
                    output_1 <= pipe_rdata_A;
                    output_2 <= pipe_rdata_B;
                    output_3 <= pipe_rdata_C;
                end
            end 
        end
    end else begin : no_memory_logic
        //This memory accomodates the 8 point 1st stage split radix fft
        //It inpus data in the same logic but multiplexes the output differently and has a different read address calculation logic
        //1st iter              //Hole memory
        // A  B  C  D             A  B  C  D
        // 0     2                0  1  2  3
        //    4     6             7  4  5  6

        //2nd iter
        // A  B  C  D
        //    1     3
        // 7     5
        
        always@(posedge clock) begin 
            if(reset) begin
                output_0 <= 0; 
                output_1 <= 0; 
                output_2 <= 0; 
                output_3 <= 0;
                pipe_rdata_A <= 0; 
                pipe_rdata_B <= 0; 
                pipe_rdata_C <= 0; 
                pipe_rdata_D <= 0;
                ea_addr_A <= 0; 
                ea_addr_B <= 0; 
                ea_addr_C <= 0; 
                ea_addr_D <= 0;
                pipe1_op <= 0; 
                pipe2_op <= 0;
            end else begin
                //Write input data in memory depending on the stide sigment we are currently in.
                if(stride_segment_counter == 1'b0) begin
                    mem_A[mem_counter] <= {input_real_0, input_imag_0};
                    mem_B[mem_counter] <= {input_real_1, input_imag_1};
                    mem_C[mem_counter] <= {input_real_2, input_imag_2};
                    mem_D[mem_counter] <= {input_real_3, input_imag_3};
                end 
                else begin
                    mem_A[mem_counter] <= {input_real_3, input_imag_3};
                    mem_B[mem_counter] <= {input_real_0, input_imag_0};
                    mem_C[mem_counter] <= {input_real_1, input_imag_1};
                    mem_D[mem_counter] <= {input_real_2, input_imag_2};
                end

                //Read stage 1 calculate the effective address before memory read
                //To easy the jod of the synthsys tools and maximize frequency

                pipe1_op <= butterfly_op_counter; //Register the read muxing signal 

                // Determine which address each memory needs to read
                case (butterfly_op_counter)
                    1'b0: ea_addr_A <= next_addr0; 
                    1'b1: ea_addr_A <= next_addr3;
                endcase

                case (butterfly_op_counter)
                    1'b0: ea_addr_B <= next_addr1;
                    1'b1: ea_addr_B <= next_addr0;
                endcase

                case (butterfly_op_counter)
                    1'b0: ea_addr_C <= next_addr2;
                    1'b1: ea_addr_C <= next_addr1;
                endcase

                case (butterfly_op_counter)
                    1'b0: ea_addr_D <= next_addr3;
                    1'b1: ea_addr_D <= next_addr2;
                endcase

                //Read stage 2 read from memory and store in pipe registers 
                pipe2_op <= pipe1_op;  //Register the read muxing signal 
                
                pipe_rdata_A <= mem_A[ea_addr_A];
                pipe_rdata_B <= mem_B[ea_addr_B];
                pipe_rdata_C <= mem_C[ea_addr_C];
                pipe_rdata_D <= mem_D[ea_addr_D];

                //Read stage 3 output muxing
                if(pipe2_op == 1'b0) begin
                    output_0 <= pipe_rdata_A;
                    output_1 <= pipe_rdata_C;
                    output_2 <= pipe_rdata_B;
                    output_3 <= pipe_rdata_D;
                end
                else begin
                    output_0 <= pipe_rdata_B;
                    output_1 <= pipe_rdata_D;
                    output_2 <= pipe_rdata_C;
                    output_3 <= pipe_rdata_A;
                end
            end 
        end
    end

    //split data into real and imaginary parts
    assign output_real_0 = output_0[2*WIDTH-1:WIDTH];
    assign output_imag_0 = output_0[WIDTH-1:0];
    assign output_real_1 = output_1[2*WIDTH-1:WIDTH];
    assign output_imag_1 = output_1[WIDTH-1:0];
    assign output_real_2 = output_2[2*WIDTH-1:WIDTH];
    assign output_imag_2 = output_2[WIDTH-1:0];
    assign output_real_3 = output_3[2*WIDTH-1:WIDTH];
    assign output_imag_3 = output_3[WIDTH-1:0];
endmodule

split_radix/tb_memory_first_stage.v
`timescale 1ns / 1ps

module tb_memory;

    // --- Parameter Overrides ---
    parameter WIDTH = 16;             // Reduced width for clean hex data tracing
    parameter DEPTH = 2;             // Set to 4 to match stage_num_bits = 1 sizing
    parameter stage_num_bits = 0;

    // --- Testbench Signals ---
    reg clock;
    reg reset;
    reg [stage_num_bits:0] stride_segment_counter;
    reg [stage_num_bits:0] butterfly_op_counter;
    reg [stage_num_bits+1:0] mem_counter;
    reg [stage_num_bits+1:0] mem_counter_read;
    
    reg [WIDTH-1:0] input_real_0, input_real_1, input_real_2, input_real_3;
    reg [WIDTH-1:0] input_imag_0, input_imag_1, input_imag_2, input_imag_3;

    wire [WIDTH-1:0] output_real_0, output_real_1, output_real_2, output_real_3;
    wire [WIDTH-1:0] output_imag_0, output_imag_1, output_imag_2, output_imag_3;

    // --- Unit Under Test (UUT) Instantiation ---
    memory_first_stage #(
        .WIDTH(WIDTH),
        .DEPTH(DEPTH),
        .stage_num_bits(stage_num_bits)
    ) uut (
        .clock(clock),
        .reset(reset),
        .stride_segment_counter(stride_segment_counter),
        .butterfly_op_counter(butterfly_op_counter),
        .mem_counter(mem_counter),
        .mem_counter_read(mem_counter_read),
        .input_real_0(input_real_0), .input_real_1(input_real_1), .input_real_2(input_real_2), .input_real_3(input_real_3),
        .input_imag_0(input_imag_0), .input_imag_1(input_imag_1), .input_imag_2(input_imag_2), .input_imag_3(input_imag_3),
        .output_real_0(output_real_0), .output_real_1(output_real_1), .output_real_2(output_real_2), .output_real_3(output_real_3),
        .output_imag_0(output_imag_0), .output_imag_1(output_imag_1), .output_imag_2(output_imag_2), .output_imag_3(output_imag_3)
    );

    // --- Clock Generator (100MHz / 10ns period) ---
    always #5 clock = ~clock;

    // --- Loop Variable ---
    integer i;

    // --- Stimulus Setup ---
    initial begin
        // Initialize all inputs
        clock = 1;
        reset = 1;
        stride_segment_counter = 0;
        butterfly_op_counter = 0;
        mem_counter = 0;
        mem_counter_read = 0;
        input_real_0 = 0; input_real_1 = 0; input_real_2 = 0; input_real_3 = 0;
        input_imag_0 = 0; input_imag_1 = 0; input_imag_2 = 0; input_imag_3 = 0;

        // Release Reset
        #20;
        reset = 0;
        #10;

        // =================================================================
        // PHASE 1: Write Routine (Stride Segment 2'b00)
        // =================================================================
        $display("[TB INFO] Starting Memory Write Phase...");
        stride_segment_counter <= 2'b00; 
        
        for (i = 0; i < 2*DEPTH; i = i + 1) begin
            // Generate easily trackable data: Real=0x1X, 0x2X... Imag=0xAX, 0xBX...
            input_real_0 <= i*4+0;  input_imag_0 <= i*4+0;
            input_real_1 <= i*4+1;  input_imag_1 <= i*4+1;
            input_real_2 <= i*4+2;  input_imag_2 <= i*4+2;
            input_real_3 <= i*4+3;  input_imag_3 <= i*4+3;
            #10;
            stride_segment_counter <= stride_segment_counter + 1; // Increment to test different segment patterns
            mem_counter <= mem_counter + 1; // Increment memory counter for next write
        end

        // Clear inputs after writing
        input_real_0 <= 0; input_imag_0 <= 0;
        input_real_1 <= 1; input_imag_1 <= 1;
        input_real_2 <= 2; input_imag_2 <= 2;
        input_real_3 <= 3; input_imag_3 <= 3;
        #10;

        // =================================================================
        // PHASE 2: Read Pipelined Routine
        // =================================================================
        $display("[TB INFO] Starting Memory Read Phase...");
        mem_counter_read = 3'b000; // Keep offset = 0 to read the first buffer half

        for (i = 0; i < 2*DEPTH; i = i + 1) begin
            #10;
            butterfly_op_counter <= butterfly_op_counter + 1; // Increment to test different read patterns
            mem_counter_read <= mem_counter_read + 1; // Increment to read next address
        end
        
        // Flush pipeline (The design has a 3-cycle read latency)
        butterfly_op_counter <= 0;
        #30;

        $display("[TB INFO] Simulation Complete.");
        $finish;
    end

    // --- Output Monitor ---
    initial begin
        $monitor("Reset=%b | Buf_Op=%b | Out0=(R:%d,I:%d) | Out1=(R:%d,I:%d) | Out2=(R:%d,I:%d) | Out3=(R:%d,I:%d)",
                 reset, butterfly_op_counter, 
                 output_real_0, output_imag_0, 
                 output_real_1, output_imag_1, 
                 output_real_2, output_imag_2, 
                 output_real_3, output_imag_3);

        // $monitor("Input Real: %d, %d, %d, %d | Input Imag: %d, %d, %d, %d",
        //          input_real_0, input_real_1, input_real_2, input_real_3,
        //          input_imag_0, input_imag_1, input_imag_2, input_imag_3);
    end

    // --- Waveform Generation and Memory Dumping ---
    integer idx; // Loop variable for tracking memory array indices

    initial begin
        // Specify the name of the VCD file
        $dumpfile("memory_simulation.vcd");
        
        // Dump all standard scalar/vector signals in the testbench scope
        $dumpvars(0, tb_memory);
        
        // Explicitly loop through and dump every element of the 2D arrays
        // Since your memory size is [0:2*DEPTH-1], we loop up to (2*DEPTH)
        for (idx = 0; idx < (2 * DEPTH); idx = idx + 1) begin
            $dumpvars(0, uut.mem_A[idx]);
            $dumpvars(0, uut.mem_B[idx]);
            $dumpvars(0, uut.mem_C[idx]);
            $dumpvars(0, uut.mem_D[idx]);
        end
    end

endmodule

split_radix/memory_simulation.vcd
$date
	Wed May 20 03:11:33 2026
$end
$version
	Icarus Verilog
$end
$timescale
	1ps
$end
$scope module tb_memory $end
$var wire 16 ! output_real_3 [15:0] $end
$var wire 16 " output_real_2 [15:0] $end
$var wire 16 # output_real_1 [15:0] $end
$var wire 16 $ output_real_0 [15:0] $end
$var wire 16 % output_imag_3 [15:0] $end
$var wire 16 & output_imag_2 [15:0] $end
$var wire 16 ' output_imag_1 [15:0] $end
$var wire 16 ( output_imag_0 [15:0] $end
$var parameter 32 ) DEPTH $end
$var parameter 32 * WIDTH $end
$var parameter 32 + stage_num_bits $end
$var reg 1 , butterfly_op_counter $end
$var reg 1 - clock $end
$var reg 16 . input_imag_0 [15:0] $end
$var reg 16 / input_imag_1 [15:0] $end
$var reg 16 0 input_imag_2 [15:0] $end
$var reg 16 1 input_imag_3 [15:0] $end
$var reg 16 2 input_real_0 [15:0] $end
$var reg 16 3 input_real_1 [15:0] $end
$var reg 16 4 input_real_2 [15:0] $end
$var reg 16 5 input_real_3 [15:0] $end
$var reg 2 6 mem_counter [1:0] $end
$var reg 2 7 mem_counter_read [1:0] $end
$var reg 1 8 reset $end
$var reg 1 9 stride_segment_counter $end
$var integer 32 : i [31:0] $end
$var integer 32 ; idx [31:0] $end
$scope module uut $end
$var wire 1 , butterfly_op_counter $end
$var wire 1 - clock $end
$var wire 16 < input_imag_0 [15:0] $end
$var wire 16 = input_imag_1 [15:0] $end
$var wire 16 > input_imag_2 [15:0] $end
$var wire 16 ? input_imag_3 [15:0] $end
$var wire 16 @ input_real_0 [15:0] $end
$var wire 16 A input_real_1 [15:0] $end
$var wire 16 B input_real_2 [15:0] $end
$var wire 16 C input_real_3 [15:0] $end
$var wire 2 D mem_counter [1:0] $end
$var wire 2 E mem_counter_read [1:0] $end
$var wire 3 F position_count [2:0] $end
$var wire 1 8 reset $end
$var wire 1 9 stride_segment_counter $end
$var wire 16 G output_real_3 [15:0] $end
$var wire 16 H output_real_2 [15:0] $end
$var wire 16 I output_real_1 [15:0] $end
$var wire 16 J output_real_0 [15:0] $end
$var wire 16 K output_imag_3 [15:0] $end
$var wire 16 L output_imag_2 [15:0] $end
$var wire 16 M output_imag_1 [15:0] $end
$var wire 16 N output_imag_0 [15:0] $end
$var wire 2 O offset [1:0] $end
$var wire 3 P next_addr3 [2:0] $end
$var wire 3 Q next_addr2 [2:0] $end
$var wire 3 R next_addr1 [2:0] $end
$var wire 3 S next_addr0 [2:0] $end
$var parameter 32 T DEPTH $end
$var parameter 32 U WIDTH $end
$var parameter 32 V inter_offset_size $end
$var parameter 33 W intra_offset_size $end
$var parameter 32 X stage_num_bits $end
$var parameter 32 Y vertical_offset_1 $end
$var parameter 32 Z vertical_offset_2 $end
$var parameter 32 [ vertical_offset_3 $end
$var reg 3 \ ea_addr_A [2:0] $end
$var reg 3 ] ea_addr_B [2:0] $end
$var reg 3 ^ ea_addr_C [2:0] $end
$var reg 3 _ ea_addr_D [2:0] $end
$var reg 32 ` output_0 [31:0] $end
$var reg 32 a output_1 [31:0] $end
$var reg 32 b output_2 [31:0] $end
$var reg 32 c output_3 [31:0] $end
$var reg 1 d pipe1_op $end
$var reg 1 e pipe2_op $end
$var reg 32 f pipe_rdata_A [31:0] $end
$var reg 32 g pipe_rdata_B [31:0] $end
$var reg 32 h pipe_rdata_C [31:0] $end
$var reg 32 i pipe_rdata_D [31:0] $end
$scope begin genblk1 $end
$upscope $end
$scope begin no_memory_logic $end
$upscope $end
$scope begin special_addresses_for_8_point_fft $end
$upscope $end
$upscope $end
$upscope $end
$scope module tb_memory $end
$scope module uut $end
$var reg 32 j \mem_A[0] [31:0] $end
$upscope $end
$upscope $end
$scope module tb_memory $end
$scope module uut $end
$var reg 32 k \mem_B[0] [31:0] $end
$upscope $end
$upscope $end
$scope module tb_memory $end
$scope module uut $end
$var reg 32 l \mem_C[0] [31:0] $end
$upscope $end
$upscope $end
$scope module tb_memory $end
$scope module uut $end
$var reg 32 m \mem_D[0] [31:0] $end
$upscope $end
$upscope $end
$scope module tb_memory $end
$scope module uut $end
$var reg 32 n \mem_A[1] [31:0] $end
$upscope $end
$upscope $end
$scope module tb_memory $end
$scope module uut $end
$var reg 32 o \mem_B[1] [31:0] $end
$upscope $end
$upscope $end
$scope module tb_memory $end
$scope module uut $end
$var reg 32 p \mem_C[1] [31:0] $end
$upscope $end
$upscope $end
$scope module tb_memory $end
$scope module uut $end
$var reg 32 q \mem_D[1] [31:0] $end
$upscope $end
$upscope $end
$scope module tb_memory $end
$scope module uut $end
$var reg 32 r \mem_A[2] [31:0] $end
$upscope $end
$upscope $end
$scope module tb_memory $end
$scope module uut $end
$var reg 32 s \mem_B[2] [31:0] $end
$upscope $end
$upscope $end
$scope module tb_memory $end
$scope module uut $end
$var reg 32 t \mem_C[2] [31:0] $end
$upscope $end
$upscope $end
$scope module tb_memory $end
$scope module uut $end
$var reg 32 u \mem_D[2] [31:0] $end
$upscope $end
$upscope $end
$scope module tb_memory $end
$scope module uut $end
$var reg 32 v \mem_A[3] [31:0] $end
$upscope $end
$upscope $end
$scope module tb_memory $end
$scope module uut $end
$var reg 32 w \mem_B[3] [31:0] $end
$upscope $end
$upscope $end
$scope module tb_memory $end
$scope module uut $end
$var reg 32 x \mem_C[3] [31:0] $end
$upscope $end
$upscope $end
$scope module tb_memory $end
$scope module uut $end
$var reg 32 y \mem_D[3] [31:0] $end
$upscope $end
$upscope $end
$enddefinitions $end
$comment Show the parameter values. $end
$dumpall
b0 [
b0 Z
b0 Y
b0 X
b111111111111111111111111111111111 W
b1 V
b10000 U
b10 T
b0 +
b10000 *
b10 )
$end
#0
$dumpvars
bx y
bx x
bx w
bx v
bx u
bx t
bx s
bx r
bx q
bx p
bx o
bx n
bx m
bx l
bx k
bx j
b0 i
b0 h
b0 g
b0 f
0e
0d
b0 c
b0 b
b0 a
b0 `
b0 _
b0 ^
b0 ]
b0 \
b0 S
b1 R
b0 Q
b1 P
b0 O
b0 N
b0 M
b0 L
b0 K
b0 J
b0 I
b0 H
b0 G
b0 F
b0 E
b0 D
b0 C
b0 B
b0 A
b0 @
b0 ?
b0 >
b0 =
b0 <
b100 ;
bx :
09
18
b0 7
b0 6
b0 5
b0 4
b0 3
b0 2
b0 1
b0 0
b0 /
b0 .
1-
0,
b0 (
b0 '
b0 &
b0 %
b0 $
b0 #
b0 "
b0 !
$end
#5000
0-
#10000
1-
#15000
0-
#20000
bx i
bx h
bx g
bx f
b1 _
b1 ]
b0 m
b0 l
b0 k
b0 j
1-
08
#25000
0-
#30000
bx !
bx G
bx %
bx K
bx "
bx H
bx &
bx L
bx #
bx I
bx '
bx M
bx $
bx J
bx (
bx N
bx c
bx b
bx a
bx `
b0 h
b0 f
b0 m
b0 l
b0 k
b0 j
b11 1
b11 ?
b11 5
b11 C
b10 0
b10 >
b10 4
b10 B
b1 /
b1 =
b1 3
b1 A
1-
b0 :
#35000
0-
#40000
b0 #
b0 I
b0 '
b0 M
b0 $
b0 J
b0 (
b0 N
b0 a
b0 `
b110000000000000011 m
b100000000000000010 l
b10000000000000001 k
b0 j
b111 1
b111 ?
b111 5
b111 C
b110 0
b110 >
b110 4
b110 B
b101 /
b101 =
b101 3
b101 A
b100 .
b100 <
b100 2
b100 @
b1 6
b1 D
19
1-
b1 :
#45000
0-
#50000
b100000000000000010 h
b1100000000000000110 q
b1010000000000000101 p
b1000000000000000100 o
b1110000000000000111 n
b1011 1
b1011 ?
b1011 5
b1011 C
b1010 0
b1010 >
b1010 4
b1010 B
b1001 /
b1001 =
b1001 3
b1001 A
b1000 .
b1000 <
b1000 2
b1000 @
b10 6
b10 D
09
1-
b10 :
#55000
0-
#60000
b10 #
b10 I
b10 '
b10 M
b100000000000000010 a
b1100000000000000110 i
b1000000000000000100 g
b10110000000000001011 u
b10100000000000001010 t
b10010000000000001001 s
b10000000000000001000 r
b1111 1
b1111 ?
b1111 5
b1111 C
b1110 0
b1110 >
b1110 4
b1110 B
b1101 /
b1101 =
b1101 3
b1101 A
b1100 .
b1100 <
b1100 2
b1100 @
b11 6
b11 D
19
1-
b11 :
#65000
0-
#70000
b110 !
b110 G
b110 %
b110 K
b100 "
b100 H
b100 &
b100 L
b1100000000000000110 c
b1000000000000000100 b
b11100000000000001110 y
b11010000000000001101 x
b11000000000000001100 w
b11110000000000001111 v
b11 1
b11 ?
b11 5
b11 C
b10 0
b10 >
b10 4
b10 B
b1 /
b1 =
b1 3
b1 A
b0 .
b0 <
b0 2
b0 @
b0 6
b0 D
09
1-
b100 :
#75000
0-
#80000
b110000000000000011 m
b100000000000000010 l
b10000000000000001 k
b0 j
1-
b0 :
#85000
0-
#90000
b110000000000000011 m
b100000000000000010 l
b10000000000000001 k
b0 j
b1 7
b1 E
1,
1-
b1 :
#95000
0-
#100000
b10 S
b11 R
b10 Q
b11 P
b10 O
b0 _
b1 ^
b0 ]
b1 \
1d
b110000000000000011 m
b100000000000000010 l
b10000000000000001 k
b0 j
b10 7
b10 E
0,
1-
b10 :
#105000
0-
#110000
b110000000000000011 i
b1010000000000000101 h
b10000000000000001 g
b1110000000000000111 f
1e
b11 _
b10 ^
b11 ]
b10 \
0d
b110000000000000011 m
b100000000000000010 l
b10000000000000001 k
b0 j
b11 7
b11 E
1,
1-
b11 :
#115000
0-
#120000
b0 S
b1 R
b0 Q
b1 P
b0 O
b111 !
b111 G
b111 %
b111 K
b101 "
b101 H
b101 &
b101 L
b11 #
b11 I
b11 '
b11 M
b1 $
b1 J
b1 (
b1 N
b1110000000000000111 c
b1010000000000000101 b
b110000000000000011 a
b10000000000000001 `
b11100000000000001110 i
b10100000000000001010 h
b11000000000000001100 g
b10000000000000001000 f
0e
b10 _
b11 ^
b10 ]
b11 \
1d
b110000000000000011 m
b100000000000000010 l
b10000000000000001 k
b0 j
b0 7
b0 E
0,
1-
b100 :
#125000
0-
#130000
b1110 !
b1110 G
b1110 %
b1110 K
b1100 "
b1100 H
b1100 &
b1100 L
b1010 #
b1010 I
b1010 '
b1010 M
b1000 $
b1000 J
b1000 (
b1000 N
b11100000000000001110 c
b11000000000000001100 b
b10100000000000001010 a
b10000000000000001000 `
b10110000000000001011 i
b11010000000000001101 h
b10010000000000001001 g
b11110000000000001111 f
1e
b1 _
b0 ^
b1 ]
b0 \
0d
b110000000000000011 m
b100000000000000010 l
b10000000000000001 k
b0 j
1-
#135000
0-
#140000
b1111 !
b1111 G
b1111 %
b1111 K
b1101 "
b1101 H
b1101 &
b1101 L
b1011 #
b1011 I
b1011 '
b1011 M
b1001 $
b1001 J
b1001 (
b1001 N
b11110000000000001111 c
b11010000000000001101 b
b10110000000000001011 a
b10010000000000001001 `
b1100000000000000110 i
b100000000000000010 h
b1000000000000000100 g
b0 f
0e
b110000000000000011 m
b100000000000000010 l
b10000000000000001 k
b0 j
1-
#145000
0-
#150000
b110 !
b110 G
b110 %
b110 K
b100 "
b100 H
b100 &
b100 L
b10 #
b10 I
b10 '
b10 M
b0 $
b0 J
b0 (
b0 N
b1100000000000000110 c
b1000000000000000100 b
b100000000000000010 a
b0 `
b110000000000000011 m
b100000000000000010 l
b10000000000000001 k
b0 j
1-
